{
  "result": {
    "pastEvents": {
      "cities": [
        {
          "id": 1,
          "name": "Middlesbrough",
          "image1": "frontend/assets/Middlesbrough/Middlesbrough1.jpg",
          "image2": "/assets/Middlesbrough/Middlesbrough2.jpg",
          "description1": "Middlesbrough Middlesbrough Middlesbrough Middlesbrough.",
          "description2": "Middlesbrough Middlesbrough Middlesbrough Middlesbrough."
        },
        {
          "id": 2,
          "name": "Stockton-on-tees",
          "image1": "/assets/Stockton-on-tees/Stockton-on-tees1.jpg",
          "image2": "/assets/Stockton-on-tees/Stockton-on-tees2.jpg",
          "description1": "Stockton-on-tees.",
          "description2": "Stockton-on-tees."
        },
        {
          "id": 3,
          "name": "London",
          "image1": "/assets/London/London1.jpg",
          "image2": "/assets/London/London2.jpg",
          "description1": "The city that never sleeps London.",
          "description2": "The city that never sleeps London."
        },
        {
          "id": 4,
          "name": "Newcastle",
          "image1": "/assets/Newcastle/Newcastle1.jpg",
          "image2": "/assets/Newcastle/Newcastle2.jpg",
          "description1": "The city that never sleeps Newcastle.",
          "description2": "The city that never sleeps Newcastle."
        },
        {
          "id": 5,
          "name": "Manchester",
          "image1": "/assets/Manchester/Manchester1.jpg",
          "image2": "/assets/Manchester/Manchester2.jpg",
          "description1": "The city that never sleeps Manchester.",
          "description2": "The city that never sleeps Manchester."
        },
        {
          "id": 6,
          "name": "Gainsborough",
          "image1": "/assets/Gainsborough/Gainsborough1.jpg",
          "image2": "/assets/Gainsborough/Gainsborough2.jpg",
          "description1": "The city that never sleeps Gainsborough.",
          "description2": "The city that never sleeps Gainsborough."
        },
        {
          "id": 7,
          "name": "Birmingham",
          "image1": "/assets/Birmingham/Birmingham1.jpg",
          "image2": "/assets/Birmingham/Birmingham2.jpg",
          "description1": "The city that never sleeps Birmingham.",
          "description2": "The city that never sleeps Birmingham."
        }
      ]
    },
    "upcomingEvents": {}
  }
}
